spanner_orm/__init__.py
spanner_orm/api.py
spanner_orm/condition.py
spanner_orm/decorator.py
spanner_orm/error.py
spanner_orm/field.py
spanner_orm/index.py
spanner_orm/metadata.py
spanner_orm/model.py
spanner_orm/query.py
spanner_orm/registry.py
spanner_orm/relationship.py
spanner_orm/table_apis.py
spanner_orm/admin/__init__.py
spanner_orm/admin/api.py
spanner_orm/admin/column.py
spanner_orm/admin/index.py
spanner_orm/admin/index_column.py
spanner_orm/admin/metadata.py
spanner_orm/admin/migration.py
spanner_orm/admin/migration.skel
spanner_orm/admin/migration_executor.py
spanner_orm/admin/migration_manager.py
spanner_orm/admin/migration_status.py
spanner_orm/admin/schema.py
spanner_orm/admin/scripts.py
spanner_orm/admin/table.py
spanner_orm/admin/update.py
spanner_orm_fork-0.1.10.dist-info/LICENSE
spanner_orm_fork-0.1.10.dist-info/METADATA
spanner_orm_fork-0.1.10.dist-info/WHEEL
spanner_orm_fork-0.1.10.dist-info/entry_points.txt
spanner_orm_fork-0.1.10.dist-info/top_level.txt
spanner_orm_fork-0.1.10.dist-info/RECORD
